emtl/__init__.py
emtl/__main__.py
emtl/cli.py
emtl/const.py
emtl/core.py
emtl/utils.py
emtl/tests/__init__.py
emtl/tests/test_cli.py
emtl/tests/test_core.py
emtl-0.2.6.dist-info/AUTHORS.rst
emtl-0.2.6.dist-info/LICENSE
emtl-0.2.6.dist-info/METADATA
emtl-0.2.6.dist-info/WHEEL
emtl-0.2.6.dist-info/entry_points.txt
emtl-0.2.6.dist-info/top_level.txt
emtl-0.2.6.dist-info/RECORD
