Metadata-Version: 2.1
Name: emtl
Version: 0.2.6
Summary: 东方财富自动交易接口
Home-page: https://github.com/riiy/emtl
Author: Riiy
Author-email: riiyzhou@gmail.com
License: MIT
Project-URL: Documentation, https://emtl.readthedocs.io/
Project-URL: Changelog, https://emtl.readthedocs.io/en/latest/changelog.html
Project-URL: Issue Tracker, https://github.com/riiy/emtl/issues
Keywords: autotrade,trade,东方财富,股票,交易,交易机器人
Classifier: Development Status :: 5 - Production/Stable
Classifier: Intended Audience :: Developers
Classifier: License :: OSI Approved :: MIT License
Classifier: Operating System :: Unix
Classifier: Operating System :: POSIX
Classifier: Programming Language :: Python
Classifier: Programming Language :: Python :: 3
Classifier: Programming Language :: Python :: 3 :: Only
Classifier: Programming Language :: Python :: 3.11
Classifier: Programming Language :: Python :: Implementation :: CPython
Classifier: Topic :: Utilities
Requires-Python: >=3.10
License-File: LICENSE
License-File: AUTHORS.rst
